nanonis_reader/__init__.py
nanonis_reader/atom_analysis.py
nanonis_reader/base.py
nanonis_reader/cmap_custom.py
nanonis_reader/dat.py
nanonis_reader/find_value.py
nanonis_reader/grid.py
nanonis_reader/nanonis_3ds.py
nanonis_reader/nanonis_dat.py
nanonis_reader/nanonis_sxm.py
nanonis_reader/schematic.py
nanonis_reader/spectral_analysis.py
nanonis_reader/sxm.py
nanonis_reader/util.py
nanonis_reader-0.1.8.dist-info/METADATA
nanonis_reader-0.1.8.dist-info/WHEEL
nanonis_reader-0.1.8.dist-info/top_level.txt
nanonis_reader-0.1.8.dist-info/RECORD
