Metadata-Version: 2.1
Name: nanonis_reader
Version: 0.1.8
Summary: A Python package for reading STM experimental data files obtained from Nanonis, based on nanonispy
Home-page: https://github.com/D-gitt/nanonis_reader
Author: Dowook Kim
Author-email: dw.kim@postech.ac.kr
Keywords: nanonis,reader,nanonispy,STM data,scientific data analysis
Classifier: Programming Language :: Python :: 3.6
Classifier: Programming Language :: Python :: 3.7
Classifier: Programming Language :: Python :: 3.8
Classifier: Programming Language :: Python :: 3.9
Classifier: License :: OSI Approved :: MIT License
Classifier: Operating System :: OS Independent
Requires-Python: >=3.6
Requires-Dist: matplotlib
Requires-Dist: nanonispy
Requires-Dist: numpy
Requires-Dist: python-pptx
Requires-Dist: scipy
